Pwgv/__init__.py
Pwgv/pwgv.py
Pwgv-1.1.dist-info/METADATA
Pwgv-1.1.dist-info/WHEEL
Pwgv-1.1.dist-info/top_level.txt
Pwgv-1.1.dist-info/RECORD
