Metadata-Version: 2.1
Name: Pwgv
Version: 1.1
Summary: pwgv (password generation and verification) модуль который состоит из инструкций генераций паролей, проверки и записи
Home-page: https://github.com/G0ga1/percent_password
Author: G0ga1
Author-email: andre.web16@gmail.com
Requires-Python: >=3.12
